pysher_khonik/__init__.py
pysher_khonik/channel.py
pysher_khonik/connection.py
pysher_khonik/pusher.py
pysher_khonik-1.0.12.dist-info/LICENSE
pysher_khonik-1.0.12.dist-info/METADATA
pysher_khonik-1.0.12.dist-info/WHEEL
pysher_khonik-1.0.12.dist-info/top_level.txt
pysher_khonik-1.0.12.dist-info/RECORD
